HISTORY.rst
LICENSE
MANIFEST.in
README.rst
setup.py
Stencil.egg-info/PKG-INFO
Stencil.egg-info/SOURCES.txt
Stencil.egg-info/dependency_links.txt
Stencil.egg-info/entry_points.txt
Stencil.egg-info/not-zip-safe
Stencil.egg-info/requires.txt
Stencil.egg-info/top_level.txt
stencil/__init__.py
stencil/base.py
stencil/main.py
stencil/resources.py
stencil/stencils.py
stencil/utils.py
stencil/variables.py
stencil/stencils/new/README_tmpl
stencil/stencils/new/setup.py_tmpl
stencil/stencils/new/{package_name}/__init__.py
stencil/stencils/new/{package_name}/stencils.py_tmpl
stencil/stencils/new/{package_name}/stencils/{command_name}/README